{"image_id": 1113, "figure": {"gender": 0, "age": 3, "height": 2, "shape": 2, "skinColor": 3, "hair": 2}, "scene": {"season": 4, "sceneClass": "31", "event": 3, "color": [[0, 0, 0], [0, 0, 0], [0, 0, 0], [0, 0, 0], [0, 0, 0]]}, "clothes": [{"clothType": 5, "UpperType": 4, "UpperLength": 5, "UpperModel": 4, "UpperCollar": 8, "UpperSleeveLength": 1, "UpperShouders": 2, "UpperCuff": 2, "UpperOpening": 2, "UpperMaterial": 4, "UpperPattern": 2, "TrousersType": 0, "TrousersWaist": 0, "TrousersLength": 0, "TrousersModel": 0, "TrousersMaterial": 0, "TrousersPattern": 0, "SkirtType": 0, "SkirtWaist": 0, "SkirtLength": 0, "SkirtFold": 0, "SkirtMaterial": 0, "SkirtPattern": 0}, {"clothType": 0, "UpperType": 0, "UpperLength": 0, "UpperModel": 0, "UpperCollar": 0, "UpperSleeveLength": 0, "UpperShouders": 0, "UpperCuff": 0, "UpperOpening": 0, "UpperMaterial": 0, "UpperPattern": 0, "TrousersType": 4, "TrousersWaist": 2, "TrousersLength": 4, "TrousersModel": 2, "TrousersMaterial": 2, "TrousersPattern": 4, "SkirtType": 0, "SkirtWaist": 0, "SkirtLength": 0, "SkirtFold": 0, "SkirtMaterial": 0, "SkirtPattern": 0}], "rate": 0}