{"image_id": "female_elder_256", "figure": {"gender": 0, "age": 2, "height": 2, "shape": 1, "skinColor": 1, "hair": 3}, "scene": {"season": 2, "sceneClass": "45", "event": 4, "color": [[194.3537380980791, 170.92359561844927, 147.5459215562943], [33.36272332410171, 33.94326888219595, 33.00588488107232], [63.806417206295144, 84.91420422089209, 91.25813436025285], [111.2456904977697, 130.86099856053536, 132.92856000426454], [231.46748355776822, 233.41305981836962, 213.84551362354858]]}, "clothes": [{"clothType": 1, "UpperType": 16, "UpperLength": 3, "UpperModel": 3, "UpperCollar": 5, "UpperSleeveLength": 2, "UpperShouders": 1, "UpperSleeve": 0, "UpperCuff": 1, "UpperOpening": 1, "UpperMaterial": 5, "UpperPattern": 1, "TrousersType": 0, "TrousersWaist": 0, "TrousersLength": 0, "TrousersModel": 0, "TrousersMaterial": 0, "TrousersPattern": 0, "SkirtType": 0, "SkirtWaist": 0, "SkirtLength": 0, "SkirtFold": 0, "SkirtMaterial": 0, "SkirtPattern": 0}, {"clothType": 2, "UpperType": 0, "UpperLength": 0, "UpperModel": 0, "UpperCollar": 0, "UpperSleeveLength": 0, "UpperShouders": 0, "UpperSleeve": 0, "UpperCuff": 0, "UpperOpening": 0, "UpperMaterial": 0, "UpperPattern": 0, "TrousersType": 5, "TrousersWaist": 2, "TrousersLength": 2, "TrousersModel": 2, "TrousersMaterial": 3, "TrousersPattern": 1, "SkirtType": 0, "SkirtWaist": 0, "SkirtLength": 0, "SkirtFold": 0, "SkirtMaterial": 0, "SkirtPattern": 0}], "rate": 1}