{"image_id": "female_elder_220", "figure": {"gender": 0, "age": 2, "height": 2, "shape": 1, "skinColor": 1, "hair": 2}, "scene": {"season": 1, "sceneClass": "45", "event": 1, "color": [[35.34006382936853, 43.01379721475347, 44.14274575223137], [79.44013748462088, 91.75205397031877, 96.36579344112853], [222.95049667777033, 218.67197048832423, 215.50217115939859], [161.38983831659414, 160.75001486059855, 152.5172160137805], [225.0352915015353, 140.21535925911323, 104.19142173213555]]}, "clothes": [{"clothType": 1, "UpperType": 10, "UpperLength": 3, "UpperModel": 3, "UpperCollar": 6, "UpperSleeveLength": 5, "UpperShouders": 1, "UpperSleeve": 0, "UpperCuff": 1, "UpperOpening": 2, "UpperMaterial": 6, "UpperPattern": 2, "TrousersType": 0, "TrousersWaist": 0, "TrousersLength": 0, "TrousersModel": 0, "TrousersMaterial": 0, "TrousersPattern": 0, "SkirtType": 0, "SkirtWaist": 0, "SkirtLength": 0, "SkirtFold": 0, "SkirtMaterial": 0, "SkirtPattern": 0}, {"clothType": 2, "UpperType": 0, "UpperLength": 0, "UpperModel": 0, "UpperCollar": 0, "UpperSleeveLength": 0, "UpperShouders": 0, "UpperSleeve": 0, "UpperCuff": 0, "UpperOpening": 0, "UpperMaterial": 0, "UpperPattern": 0, "TrousersType": 2, "TrousersWaist": 2, "TrousersLength": 4, "TrousersModel": 2, "TrousersMaterial": 6, "TrousersPattern": 2, "SkirtType": 0, "SkirtWaist": 0, "SkirtLength": 0, "SkirtFold": 0, "SkirtMaterial": 0, "SkirtPattern": 0}], "rate": 1}