{"image_id": "female_elder_235", "figure": {"gender": 0, "age": 2, "height": 2, "shape": 2, "skinColor": 3, "hair": 3}, "scene": {"season": 3, "sceneClass": "32", "event": 4, "color": [[84.63344868671437, 77.29744827056766, 70.4919628325806], [122.5321026276548, 113.15060401805877, 105.38674031757074], [171.08509938963266, 148.42805382824335, 138.29065878835766], [30.849333800168495, 28.376037397818166, 26.775036553509892], [233.5964556498437, 199.8896070337258, 195.71425393980607]]}, "clothes": [{"clothType": 1, "UpperType": 8, "UpperLength": 4, "UpperModel": 4, "UpperCollar": 6, "UpperSleeveLength": 5, "UpperShouders": 1, "UpperSleeve": 0, "UpperCuff": 1, "UpperOpening": 2, "UpperMaterial": 1, "UpperPattern": 1, "TrousersType": 0, "TrousersWaist": 0, "TrousersLength": 0, "TrousersModel": 0, "TrousersMaterial": 0, "TrousersPattern": 0, "SkirtType": 0, "SkirtWaist": 0, "SkirtLength": 0, "SkirtFold": 0, "SkirtMaterial": 0, "SkirtPattern": 0}, {"clothType": 2, "UpperType": 0, "UpperLength": 0, "UpperModel": 0, "UpperCollar": 0, "UpperSleeveLength": 0, "UpperShouders": 0, "UpperSleeve": 0, "UpperCuff": 0, "UpperOpening": 0, "UpperMaterial": 0, "UpperPattern": 0, "TrousersType": 2, "TrousersWaist": 2, "TrousersLength": 4, "TrousersModel": 2, "TrousersMaterial": 6, "TrousersPattern": 1, "SkirtType": 0, "SkirtWaist": 0, "SkirtLength": 0, "SkirtFold": 0, "SkirtMaterial": 0, "SkirtPattern": 0}], "rate": 1}