{"image_id": "holding_an_umbrella_427", "figure": {"gender": 1, "age": 1, "height": 1, "shape": 2, "skinColor": 1, "hair": 2}, "scene": {"season": 3, "sceneClass": "46", "event": 1, "color": [[150.43938354845397, 126.1452899248719, 118.75850510498715], [41.25242528264238, 41.382009999613345, 39.53732136861311], [96.27481336116321, 87.11213905242838, 78.36585365853648], [187.5115576387289, 169.59246644814002, 162.89485484888309], [233.39582665736634, 223.23345460026584, 219.47659799061182]]}, "clothes": [{"clothType": 1, "UpperType": 7, "UpperLength": 3, "UpperModel": 3, "UpperCollar": 8, "UpperSleeveLength": 5, "UpperShouders": 1, "UpperSleeve": 0, "UpperCuff": 1, "UpperOpening": 1, "UpperMaterial": 5, "UpperPattern": 3, "TrousersType": 0, "TrousersWaist": 0, "TrousersLength": 0, "TrousersModel": 0, "TrousersMaterial": 0, "TrousersPattern": 0, "SkirtType": 0, "SkirtWaist": 0, "SkirtLength": 0, "SkirtFold": 0, "SkirtMaterial": 0, "SkirtPattern": 0}, {"clothType": 2, "UpperType": 0, "UpperLength": 0, "UpperModel": 0, "UpperCollar": 0, "UpperSleeveLength": 0, "UpperShouders": 0, "UpperSleeve": 0, "UpperCuff": 0, "UpperOpening": 0, "UpperMaterial": 0, "UpperPattern": 0, "TrousersType": 2, "TrousersWaist": 2, "TrousersLength": 4, "TrousersModel": 3, "TrousersMaterial": 6, "TrousersPattern": 1, "SkirtType": 0, "SkirtWaist": 0, "SkirtLength": 0, "SkirtFold": 0, "SkirtMaterial": 0, "SkirtPattern": 0}], "rate": 1}