{"image_id": "male_child_475", "figure": {"gender": 1, "age": 1, "height": 2, "shape": 2, "skinColor": 3, "hair": 1}, "scene": {"season": 3, "sceneClass": "45", "event": 6, "color": [[250.65163435573805, 244.6032173413832, 242.08416356460077], [218.17757851206736, 207.52114494847143, 205.85573182905677], [15.729971440170289, 10.794852325845511, 13.037554897847599], [186.5786003255684, 151.40212650507257, 140.56475331580052], [112.32254895540612, 73.59533695722926, 74.45065164712423]]}, "clothes": [{"clothType": 1, "UpperType": 1, "UpperLength": 3, "UpperModel": 3, "UpperCollar": 4, "UpperSleeveLength": 5, "UpperShouders": 1, "UpperSleeve": 0, "UpperCuff": 1, "UpperOpening": 2, "UpperMaterial": 5, "UpperPattern": 1, "TrousersType": 0, "TrousersWaist": 0, "TrousersLength": 0, "TrousersModel": 0, "TrousersMaterial": 0, "TrousersPattern": 0, "SkirtType": 0, "SkirtWaist": 0, "SkirtLength": 0, "SkirtFold": 0, "SkirtMaterial": 0, "SkirtPattern": 0}, {"clothType": 2, "UpperType": 0, "UpperLength": 0, "UpperModel": 0, "UpperCollar": 0, "UpperSleeveLength": 0, "UpperShouders": 0, "UpperSleeve": 0, "UpperCuff": 0, "UpperOpening": 0, "UpperMaterial": 0, "UpperPattern": 0, "TrousersType": 1, "TrousersWaist": 2, "TrousersLength": 4, "TrousersModel": 2, "TrousersMaterial": 5, "TrousersPattern": 1, "SkirtType": 0, "SkirtWaist": 0, "SkirtLength": 0, "SkirtFold": 0, "SkirtMaterial": 0, "SkirtPattern": 0}, {"clothType": 1, "UpperType": 5, "UpperLength": 3, "UpperModel": 3, "UpperCollar": 6, "UpperSleeveLength": 5, "UpperShouders": 1, "UpperSleeve": 0, "UpperCuff": 1, "UpperOpening": 2, "UpperMaterial": 5, "UpperPattern": 1, "TrousersType": 0, "TrousersWaist": 0, "TrousersLength": 0, "TrousersModel": 0, "TrousersMaterial": 0, "TrousersPattern": 0, "SkirtType": 0, "SkirtWaist": 0, "SkirtLength": 0, "SkirtFold": 0, "SkirtMaterial": 0, "SkirtPattern": 0}], "rate": 1}