{"image_id": "male_child_462", "figure": {"gender": 1, "age": 1, "height": 2, "shape": 2, "skinColor": 1, "hair": 2}, "scene": {"season": 3, "sceneClass": "1", "event": 6, "color": [[216.4634365158713, 213.58748138563365, 206.6235383150697], [154.93529552907268, 161.9793049668083, 173.4265109707051], [48.197892787361084, 26.42073108757627, 31.817363612762733], [93.72666831992744, 94.78302098463185, 106.03579315312686], [229.65427578336522, 79.92231154976922, 48.598052482169365]]}, "clothes": [{"clothType": 1, "UpperType": 1, "UpperLength": 3, "UpperModel": 3, "UpperCollar": 6, "UpperSleeveLength": 5, "UpperShouders": 1, "UpperSleeve": 0, "UpperCuff": 1, "UpperOpening": 2, "UpperMaterial": 5, "UpperPattern": 3, "TrousersType": 0, "TrousersWaist": 0, "TrousersLength": 0, "TrousersModel": 0, "TrousersMaterial": 0, "TrousersPattern": 0, "SkirtType": 0, "SkirtWaist": 0, "SkirtLength": 0, "SkirtFold": 0, "SkirtMaterial": 0, "SkirtPattern": 0}, {"clothType": 1, "UpperType": 14, "UpperLength": 3, "UpperModel": 3, "UpperCollar": 5, "UpperSleeveLength": 5, "UpperShouders": 1, "UpperSleeve": 0, "UpperCuff": 1, "UpperOpening": 1, "UpperMaterial": 5, "UpperPattern": 1, "TrousersType": 0, "TrousersWaist": 0, "TrousersLength": 0, "TrousersModel": 0, "TrousersMaterial": 0, "TrousersPattern": 0, "SkirtType": 0, "SkirtWaist": 0, "SkirtLength": 0, "SkirtFold": 0, "SkirtMaterial": 0, "SkirtPattern": 0}, {"clothType": 2, "UpperType": 0, "UpperLength": 0, "UpperModel": 0, "UpperCollar": 0, "UpperSleeveLength": 0, "UpperShouders": 0, "UpperSleeve": 0, "UpperCuff": 0, "UpperOpening": 0, "UpperMaterial": 0, "UpperPattern": 0, "TrousersType": 2, "TrousersWaist": 2, "TrousersLength": 4, "TrousersModel": 2, "TrousersMaterial": 5, "TrousersPattern": 2, "SkirtType": 0, "SkirtWaist": 0, "SkirtLength": 0, "SkirtFold": 0, "SkirtMaterial": 0, "SkirtPattern": 0}], "rate": 1}