{"image_id": "playing_guitar_537", "figure": {"gender": 1, "age": 2, "height": 2, "shape": 2, "skinColor": 1, "hair": 3}, "scene": {"season": 4, "sceneClass": "44", "event": 1, "color": [[189.71652536846267, 209.7240902569501, 191.88159645233554], [17.285079954726626, 20.372725425893293, 27.52746901936277], [63.540869368691105, 77.81365827934309, 79.72028024709961], [124.6471522264415, 137.77459440800854, 129.8660683465649], [212.57438848920907, 77.82762589928058, 18.617553956834016]]}, "clothes": [{"clothType": 1, "UpperType": 4, "UpperLength": 4, "UpperModel": 4, "UpperCollar": 8, "UpperSleeveLength": 5, "UpperShouders": 1, "UpperSleeve": 0, "UpperCuff": 1, "UpperOpening": 3, "UpperMaterial": 6, "UpperPattern": 1, "TrousersType": 0, "TrousersWaist": 0, "TrousersLength": 0, "TrousersModel": 0, "TrousersMaterial": 0, "TrousersPattern": 0, "SkirtType": 0, "SkirtWaist": 0, "SkirtLength": 0, "SkirtFold": 0, "SkirtMaterial": 0, "SkirtPattern": 0}, {"clothType": 2, "UpperType": 0, "UpperLength": 0, "UpperModel": 0, "UpperCollar": 0, "UpperSleeveLength": 0, "UpperShouders": 0, "UpperSleeve": 0, "UpperCuff": 0, "UpperOpening": 0, "UpperMaterial": 0, "UpperPattern": 0, "TrousersType": 2, "TrousersWaist": 2, "TrousersLength": 4, "TrousersModel": 2, "TrousersMaterial": 6, "TrousersPattern": 1, "SkirtType": 0, "SkirtWaist": 0, "SkirtLength": 0, "SkirtFold": 0, "SkirtMaterial": 0, "SkirtPattern": 0}], "rate": 1}