{"image_id": "running_596", "figure": {"gender": 0, "age": 2, "height": 2, "shape": 2, "skinColor": 1, "hair": 2}, "scene": {"season": 2, "sceneClass": "63", "event": 2, "color": [[55.325701749451945, 71.68869888057644, 39.45384485571202], [15.675400907715257, 40.05579425113595, 12.335249621784016], [98.4264599333433, 97.30394145776, 66.7745254310969], [167.69095883596623, 142.74928491481262, 104.84330307175641], [213.37221418234455, 206.65557163531213, 193.102460202604]]}, "clothes": [{"clothType": 1, "UpperType": 11, "UpperLength": 1, "UpperModel": 1, "UpperCollar": 9, "UpperSleeveLength": 1, "UpperShouders": 3, "UpperSleeve": 0, "UpperCuff": 3, "UpperOpening": 1, "UpperMaterial": 5, "UpperPattern": 1, "TrousersType": 0, "TrousersWaist": 0, "TrousersLength": 0, "TrousersModel": 0, "TrousersMaterial": 0, "TrousersPattern": 0, "SkirtType": 0, "SkirtWaist": 0, "SkirtLength": 0, "SkirtFold": 0, "SkirtMaterial": 0, "SkirtPattern": 0}, {"clothType": 2, "UpperType": 0, "UpperLength": 0, "UpperModel": 0, "UpperCollar": 0, "UpperSleeveLength": 0, "UpperShouders": 0, "UpperSleeve": 0, "UpperCuff": 0, "UpperOpening": 0, "UpperMaterial": 0, "UpperPattern": 0, "TrousersType": 4, "TrousersWaist": 2, "TrousersLength": 1, "TrousersModel": 1, "TrousersMaterial": 5, "TrousersPattern": 1, "SkirtType": 0, "SkirtWaist": 0, "SkirtLength": 0, "SkirtFold": 0, "SkirtMaterial": 0, "SkirtPattern": 0}], "rate": 1}